pyepal/__init__.py
pyepal/_version.py
pyepal/models/__init__.py
pyepal/models/coregionalized.py
pyepal/models/gbdt.py
pyepal/models/gpr.py
pyepal/models/nt.py
pyepal/pal/__init__.py
pyepal/pal/_hypervolume.py
pyepal/pal/core.py
pyepal/pal/pal_base.py
pyepal/pal/pal_coregionalized.py
pyepal/pal/pal_finite_ensemble.py
pyepal/pal/pal_gbdt.py
pyepal/pal/pal_gpy.py
pyepal/pal/pal_neural_tangent.py
pyepal/pal/pal_sklearn.py
pyepal/pal/schedules.py
pyepal/pal/utils.py
pyepal/pal/validate_inputs.py
pyepal/plotting/__init__.py
pypal/__init__.py
pypal/_version.py
pypal/models/__init__.py
pypal/models/coregionalized.py
pypal/models/gbdt.py
pypal/models/gpr.py
pypal/pal/__init__.py
pypal/pal/_hypervolume.py
pypal/pal/core.py
pypal/pal/pal_base.py
pypal/pal/pal_coregionalized.py
pypal/pal/pal_gbdt.py
pypal/pal/pal_gpy.py
pypal/pal/pal_sklearn.py
pypal/pal/schedules.py
pypal/pal/utils.py
pypal/pal/validate_inputs.py
pypal/plotting/__init__.py
pyepal-0.6.1.dist-info/LICENSE
pyepal-0.6.1.dist-info/METADATA
pyepal-0.6.1.dist-info/WHEEL
pyepal-0.6.1.dist-info/top_level.txt
pyepal-0.6.1.dist-info/RECORD
