Metadata-Version: 2.1
Name: pyepal
Version: 0.6.1
Summary: PyePAL implemented the epsilon-PAL active learning algorithm
Home-page: https://github.com/kjappelbaum/PyePAL
Author: PyePAL authors
Author-email: kevin.jablonka@epfl.ch, brian.yoo@basf.com
License: Apache 2.0
Platform: UNKNOWN
Classifier: Programming Language :: Python :: 3
Classifier: Programming Language :: Python :: 3 :: Only
Classifier: Programming Language :: Python :: 3.7
Classifier: Programming Language :: Python :: 3.8
Classifier: Development Status :: 4 - Beta
Classifier: Intended Audience :: Science/Research
Classifier: License :: OSI Approved :: Apache Software License
Classifier: Operating System :: OS Independent
Classifier: Topic :: Scientific/Engineering
Classifier: Topic :: Scientific/Engineering :: Physics
Classifier: Topic :: Scientific/Engineering :: Chemistry
Classifier: Topic :: Software Development :: Libraries :: Python Modules
Classifier: Topic :: Scientific/Engineering :: Artificial Intelligence
Requires-Dist: numpy (==1.*)
Requires-Dist: numba (==0.*)
Requires-Dist: scikit-learn (==0.*)
Provides-Extra: gbdt
Requires-Dist: lightgbm (==3.*) ; extra == 'gbdt'
Provides-Extra: gpy
Requires-Dist: GPy (~=1.9.9) ; extra == 'gpy'
Requires-Dist: matplotlib (==3.*) ; extra == 'gpy'
Provides-Extra: all
Requires-Dist: neural-tangents (==0.*) ; extra == 'all'
Requires-Dist: jaxlib (==0.*) ; extra == 'all'
Requires-Dist: lightgbm (==3.*) ; extra == 'all'
Requires-Dist: GPy (~=1.9.9) ; extra == 'all'
Requires-Dist: matplotlib (==3.*) ; extra == 'all'
Provides-Extra: dev
Requires-Dist: versioneer (==0.*) ; extra == 'dev'
Requires-Dist: black (==20.*) ; extra == 'dev'
Provides-Extra: docs
Requires-Dist: sphinx (==3.*) ; extra == 'docs'
Requires-Dist: sphinx-book-theme (==0.*) ; extra == 'docs'
Requires-Dist: sphinx-autodoc-typehints (==1.*) ; extra == 'docs'
Requires-Dist: sphinx-copybutton (==0.*) ; extra == 'docs'
Provides-Extra: neural_tangents
Requires-Dist: neural-tangents (==0.*) ; extra == 'neural_tangents'
Requires-Dist: jaxlib (==0.*) ; extra == 'neural_tangents'
Provides-Extra: pre-commit
Requires-Dist: pre-commit (==2.*) ; extra == 'pre-commit'
Requires-Dist: pylint (==2.*) ; extra == 'pre-commit'
Requires-Dist: isort (==5.*) ; extra == 'pre-commit'
Provides-Extra: testing
Requires-Dist: pytest (==6.*) ; extra == 'testing'
Requires-Dist: pytest-cov (==2.*) ; extra == 'testing'
